xplinter/__init__.py
xplinter/placeholder.py
xplinter-0.0.0.dist-info/LICENSE
xplinter-0.0.0.dist-info/METADATA
xplinter-0.0.0.dist-info/WHEEL
xplinter-0.0.0.dist-info/top_level.txt
xplinter-0.0.0.dist-info/RECORD
