Metadata-Version: 2.1
Name: xplinter
Version: 0.0.0
Summary: An easy-to-use XML shredder
Author-email: Yohai Meiron <yohai.meiron@scinet.utoronto.ca>
License: GNU GENERAL PUBLIC LICENSE
Classifier: Programming Language :: Python :: 3
Classifier: License :: OSI Approved :: GNU General Public License v3 (GPLv3)
Classifier: Operating System :: OS Independent
Requires-Python: >=3.8
License-File: LICENSE
